package com.bda.controller;

import android.os.Binder;
import android.os.IBinder;
import android.os.IInterface;
import android.os.Parcel;
import android.os.RemoteException;

public abstract interface IControllerService
  extends IInterface
{
  public abstract void allowNewConnections()
    throws RemoteException;
  
  public abstract void disallowNewConnections()
    throws RemoteException;
  
  public abstract float getAxisValue(int paramInt1, int paramInt2)
    throws RemoteException;
  
  public abstract int getInfo(int paramInt)
    throws RemoteException;
  
  public abstract int getKeyCode(int paramInt1, int paramInt2)
    throws RemoteException;
  
  public abstract int getKeyCode2(int paramInt1, int paramInt2)
    throws RemoteException;
  
  public abstract int getState(int paramInt1, int paramInt2)
    throws RemoteException;
  
  public abstract boolean isAllowingNewConnections()
    throws RemoteException;
  
  public abstract void registerListener(IControllerListener paramIControllerListener, int paramInt)
    throws RemoteException;
  
  public abstract void registerListener2(IControllerListener paramIControllerListener, int paramInt)
    throws RemoteException;
  
  public abstract void registerMonitor(IControllerMonitor paramIControllerMonitor, int paramInt)
    throws RemoteException;
  
  public abstract void sendMessage(int paramInt1, int paramInt2)
    throws RemoteException;
  
  public abstract void unregisterListener(IControllerListener paramIControllerListener, int paramInt)
    throws RemoteException;
  
  public abstract void unregisterMonitor(IControllerMonitor paramIControllerMonitor, int paramInt)
    throws RemoteException;
  
  public static abstract class Stub
    extends Binder
    implements IControllerService
  {
    private static final String DESCRIPTOR = "com.bda.controller.IControllerService";
    static final int TRANSACTION_allowNewConnections = 12;
    static final int TRANSACTION_disallowNewConnections = 13;
    static final int TRANSACTION_getAxisValue = 7;
    static final int TRANSACTION_getInfo = 5;
    static final int TRANSACTION_getKeyCode = 6;
    static final int TRANSACTION_getKeyCode2 = 11;
    static final int TRANSACTION_getState = 8;
    static final int TRANSACTION_isAllowingNewConnections = 14;
    static final int TRANSACTION_registerListener = 1;
    static final int TRANSACTION_registerListener2 = 10;
    static final int TRANSACTION_registerMonitor = 3;
    static final int TRANSACTION_sendMessage = 9;
    static final int TRANSACTION_unregisterListener = 2;
    static final int TRANSACTION_unregisterMonitor = 4;
    
    public Stub()
    {
      attachInterface(this, "com.bda.controller.IControllerService");
    }
    
    public static IControllerService asInterface(IBinder paramIBinder)
    {
      if (paramIBinder == null) {
        return null;
      }
      IInterface localIInterface = paramIBinder.queryLocalInterface("com.bda.controller.IControllerService");
      if ((localIInterface != null) && ((localIInterface instanceof IControllerService))) {
        return (IControllerService)localIInterface;
      }
      return new Proxy(paramIBinder);
    }
    
    public IBinder asBinder()
    {
      return this;
    }
    
    public boolean onTransact(int paramInt1, Parcel paramParcel1, Parcel paramParcel2, int paramInt2)
      throws RemoteException
    {
      switch (paramInt1)
      {
      default: 
        return super.onTransact(paramInt1, paramParcel1, paramParcel2, paramInt2);
      case 1598968902: 
        paramParcel2.writeString("com.bda.controller.IControllerService");
        return true;
      case 1: 
        paramParcel1.enforceInterface("com.bda.controller.IControllerService");
        registerListener(IControllerListener.Stub.asInterface(paramParcel1.readStrongBinder()), paramParcel1.readInt());
        paramParcel2.writeNoException();
        return true;
      case 2: 
        paramParcel1.enforceInterface("com.bda.controller.IControllerService");
        unregisterListener(IControllerListener.Stub.asInterface(paramParcel1.readStrongBinder()), paramParcel1.readInt());
        paramParcel2.writeNoException();
        return true;
      case 3: 
        paramParcel1.enforceInterface("com.bda.controller.IControllerService");
        registerMonitor(IControllerMonitor.Stub.asInterface(paramParcel1.readStrongBinder()), paramParcel1.readInt());
        paramParcel2.writeNoException();
        return true;
      case 4: 
        paramParcel1.enforceInterface("com.bda.controller.IControllerService");
        unregisterMonitor(IControllerMonitor.Stub.asInterface(paramParcel1.readStrongBinder()), paramParcel1.readInt());
        paramParcel2.writeNoException();
        return true;
      case 5: 
        paramParcel1.enforceInterface("com.bda.controller.IControllerService");
        int n = getInfo(paramParcel1.readInt());
        paramParcel2.writeNoException();
        paramParcel2.writeInt(n);
        return true;
      case 6: 
        paramParcel1.enforceInterface("com.bda.controller.IControllerService");
        int m = getKeyCode(paramParcel1.readInt(), paramParcel1.readInt());
        paramParcel2.writeNoException();
        paramParcel2.writeInt(m);
        return true;
      case 7: 
        paramParcel1.enforceInterface("com.bda.controller.IControllerService");
        float f = getAxisValue(paramParcel1.readInt(), paramParcel1.readInt());
        paramParcel2.writeNoException();
        paramParcel2.writeFloat(f);
        return true;
      case 8: 
        paramParcel1.enforceInterface("com.bda.controller.IControllerService");
        int k = getState(paramParcel1.readInt(), paramParcel1.readInt());
        paramParcel2.writeNoException();
        paramParcel2.writeInt(k);
        return true;
      case 9: 
        paramParcel1.enforceInterface("com.bda.controller.IControllerService");
        sendMessage(paramParcel1.readInt(), paramParcel1.readInt());
        paramParcel2.writeNoException();
        return true;
      case 10: 
        paramParcel1.enforceInterface("com.bda.controller.IControllerService");
        registerListener2(IControllerListener.Stub.asInterface(paramParcel1.readStrongBinder()), paramParcel1.readInt());
        paramParcel2.writeNoException();
        return true;
      case 11: 
        paramParcel1.enforceInterface("com.bda.controller.IControllerService");
        int j = getKeyCode2(paramParcel1.readInt(), paramParcel1.readInt());
        paramParcel2.writeNoException();
        paramParcel2.writeInt(j);
        return true;
      case 12: 
        paramParcel1.enforceInterface("com.bda.controller.IControllerService");
        allowNewConnections();
        paramParcel2.writeNoException();
        return true;
      case 13: 
        paramParcel1.enforceInterface("com.bda.controller.IControllerService");
        disallowNewConnections();
        paramParcel2.writeNoException();
        return true;
      }
      paramParcel1.enforceInterface("com.bda.controller.IControllerService");
      boolean bool = isAllowingNewConnections();
      paramParcel2.writeNoException();
      if (bool) {}
      for (int i = 1;; i = 0)
      {
        paramParcel2.writeInt(i);
        return true;
      }
    }
    
    private static class Proxy
      implements IControllerService
    {
      private IBinder mRemote;
      
      Proxy(IBinder paramIBinder)
      {
        this.mRemote = paramIBinder;
      }
      
      public void allowNewConnections()
        throws RemoteException
      {
        Parcel localParcel1 = Parcel.obtain();
        Parcel localParcel2 = Parcel.obtain();
        try
        {
          localParcel1.writeInterfaceToken("com.bda.controller.IControllerService");
          this.mRemote.transact(12, localParcel1, localParcel2, 0);
          localParcel2.readException();
          return;
        }
        finally
        {
          localParcel2.recycle();
          localParcel1.recycle();
        }
      }
      
      public IBinder asBinder()
      {
        return this.mRemote;
      }
      
      public void disallowNewConnections()
        throws RemoteException
      {
        Parcel localParcel1 = Parcel.obtain();
        Parcel localParcel2 = Parcel.obtain();
        try
        {
          localParcel1.writeInterfaceToken("com.bda.controller.IControllerService");
          this.mRemote.transact(13, localParcel1, localParcel2, 0);
          localParcel2.readException();
          return;
        }
        finally
        {
          localParcel2.recycle();
          localParcel1.recycle();
        }
      }
      
      public float getAxisValue(int paramInt1, int paramInt2)
        throws RemoteException
      {
        Parcel localParcel1 = Parcel.obtain();
        Parcel localParcel2 = Parcel.obtain();
        try
        {
          localParcel1.writeInterfaceToken("com.bda.controller.IControllerService");
          localParcel1.writeInt(paramInt1);
          localParcel1.writeInt(paramInt2);
          this.mRemote.transact(7, localParcel1, localParcel2, 0);
          localParcel2.readException();
          float f = localParcel2.readFloat();
          return f;
        }
        finally
        {
          localParcel2.recycle();
          localParcel1.recycle();
        }
      }
      
      public int getInfo(int paramInt)
        throws RemoteException
      {
        Parcel localParcel1 = Parcel.obtain();
        Parcel localParcel2 = Parcel.obtain();
        try
        {
          localParcel1.writeInterfaceToken("com.bda.controller.IControllerService");
          localParcel1.writeInt(paramInt);
          this.mRemote.transact(5, localParcel1, localParcel2, 0);
          localParcel2.readException();
          int i = localParcel2.readInt();
          return i;
        }
        finally
        {
          localParcel2.recycle();
          localParcel1.recycle();
        }
      }
      
      public String getInterfaceDescriptor()
      {
        return "com.bda.controller.IControllerService";
      }
      
      public int getKeyCode(int paramInt1, int paramInt2)
        throws RemoteException
      {
        Parcel localParcel1 = Parcel.obtain();
        Parcel localParcel2 = Parcel.obtain();
        try
        {
          localParcel1.writeInterfaceToken("com.bda.controller.IControllerService");
          localParcel1.writeInt(paramInt1);
          localParcel1.writeInt(paramInt2);
          this.mRemote.transact(6, localParcel1, localParcel2, 0);
          localParcel2.readException();
          int i = localParcel2.readInt();
          return i;
        }
        finally
        {
          localParcel2.recycle();
          localParcel1.recycle();
        }
      }
      
      public int getKeyCode2(int paramInt1, int paramInt2)
        throws RemoteException
      {
        Parcel localParcel1 = Parcel.obtain();
        Parcel localParcel2 = Parcel.obtain();
        try
        {
          localParcel1.writeInterfaceToken("com.bda.controller.IControllerService");
          localParcel1.writeInt(paramInt1);
          localParcel1.writeInt(paramInt2);
          this.mRemote.transact(11, localParcel1, localParcel2, 0);
          localParcel2.readException();
          int i = localParcel2.readInt();
          return i;
        }
        finally
        {
          localParcel2.recycle();
          localParcel1.recycle();
        }
      }
      
      public int getState(int paramInt1, int paramInt2)
        throws RemoteException
      {
        Parcel localParcel1 = Parcel.obtain();
        Parcel localParcel2 = Parcel.obtain();
        try
        {
          localParcel1.writeInterfaceToken("com.bda.controller.IControllerService");
          localParcel1.writeInt(paramInt1);
          localParcel1.writeInt(paramInt2);
          this.mRemote.transact(8, localParcel1, localParcel2, 0);
          localParcel2.readException();
          int i = localParcel2.readInt();
          return i;
        }
        finally
        {
          localParcel2.recycle();
          localParcel1.recycle();
        }
      }
      
      public boolean isAllowingNewConnections()
        throws RemoteException
      {
        Parcel localParcel1 = Parcel.obtain();
        Parcel localParcel2 = Parcel.obtain();
        try
        {
          localParcel1.writeInterfaceToken("com.bda.controller.IControllerService");
          this.mRemote.transact(14, localParcel1, localParcel2, 0);
          localParcel2.readException();
          int i = localParcel2.readInt();
          boolean bool = false;
          if (i != 0) {
            bool = true;
          }
          return bool;
        }
        finally
        {
          localParcel2.recycle();
          localParcel1.recycle();
        }
      }
      
      /* Error */
      public void registerListener(IControllerListener paramIControllerListener, int paramInt)
        throws RemoteException
      {
        // Byte code:
        //   0: invokestatic 24	android/os/Parcel:obtain	()Landroid/os/Parcel;
        //   3: astore_3
        //   4: invokestatic 24	android/os/Parcel:obtain	()Landroid/os/Parcel;
        //   7: astore 4
        //   9: aload_3
        //   10: ldc 26
        //   12: invokevirtual 30	android/os/Parcel:writeInterfaceToken	(Ljava/lang/String;)V
        //   15: aload_1
        //   16: ifnull +52 -> 68
        //   19: aload_1
        //   20: invokeinterface 75 1 0
        //   25: astore 6
        //   27: aload_3
        //   28: aload 6
        //   30: invokevirtual 78	android/os/Parcel:writeStrongBinder	(Landroid/os/IBinder;)V
        //   33: aload_3
        //   34: iload_2
        //   35: invokevirtual 51	android/os/Parcel:writeInt	(I)V
        //   38: aload_0
        //   39: getfield 15	com/bda/controller/IControllerService$Stub$Proxy:mRemote	Landroid/os/IBinder;
        //   42: iconst_1
        //   43: aload_3
        //   44: aload 4
        //   46: iconst_0
        //   47: invokeinterface 36 5 0
        //   52: pop
        //   53: aload 4
        //   55: invokevirtual 39	android/os/Parcel:readException	()V
        //   58: aload 4
        //   60: invokevirtual 42	android/os/Parcel:recycle	()V
        //   63: aload_3
        //   64: invokevirtual 42	android/os/Parcel:recycle	()V
        //   67: return
        //   68: aconst_null
        //   69: astore 6
        //   71: goto -44 -> 27
        //   74: astore 5
        //   76: aload 4
        //   78: invokevirtual 42	android/os/Parcel:recycle	()V
        //   81: aload_3
        //   82: invokevirtual 42	android/os/Parcel:recycle	()V
        //   85: aload 5
        //   87: athrow
        // Local variable table:
        //   start	length	slot	name	signature
        //   0	88	0	this	Proxy
        //   0	88	1	paramIControllerListener	IControllerListener
        //   0	88	2	paramInt	int
        //   3	79	3	localParcel1	Parcel
        //   7	70	4	localParcel2	Parcel
        //   74	12	5	localObject	Object
        //   25	45	6	localIBinder	IBinder
        // Exception table:
        //   from	to	target	type
        //   9	15	74	finally
        //   19	27	74	finally
        //   27	58	74	finally
      }
      
      /* Error */
      public void registerListener2(IControllerListener paramIControllerListener, int paramInt)
        throws RemoteException
      {
        // Byte code:
        //   0: invokestatic 24	android/os/Parcel:obtain	()Landroid/os/Parcel;
        //   3: astore_3
        //   4: invokestatic 24	android/os/Parcel:obtain	()Landroid/os/Parcel;
        //   7: astore 4
        //   9: aload_3
        //   10: ldc 26
        //   12: invokevirtual 30	android/os/Parcel:writeInterfaceToken	(Ljava/lang/String;)V
        //   15: aload_1
        //   16: ifnull +53 -> 69
        //   19: aload_1
        //   20: invokeinterface 75 1 0
        //   25: astore 6
        //   27: aload_3
        //   28: aload 6
        //   30: invokevirtual 78	android/os/Parcel:writeStrongBinder	(Landroid/os/IBinder;)V
        //   33: aload_3
        //   34: iload_2
        //   35: invokevirtual 51	android/os/Parcel:writeInt	(I)V
        //   38: aload_0
        //   39: getfield 15	com/bda/controller/IControllerService$Stub$Proxy:mRemote	Landroid/os/IBinder;
        //   42: bipush 10
        //   44: aload_3
        //   45: aload 4
        //   47: iconst_0
        //   48: invokeinterface 36 5 0
        //   53: pop
        //   54: aload 4
        //   56: invokevirtual 39	android/os/Parcel:readException	()V
        //   59: aload 4
        //   61: invokevirtual 42	android/os/Parcel:recycle	()V
        //   64: aload_3
        //   65: invokevirtual 42	android/os/Parcel:recycle	()V
        //   68: return
        //   69: aconst_null
        //   70: astore 6
        //   72: goto -45 -> 27
        //   75: astore 5
        //   77: aload 4
        //   79: invokevirtual 42	android/os/Parcel:recycle	()V
        //   82: aload_3
        //   83: invokevirtual 42	android/os/Parcel:recycle	()V
        //   86: aload 5
        //   88: athrow
        // Local variable table:
        //   start	length	slot	name	signature
        //   0	89	0	this	Proxy
        //   0	89	1	paramIControllerListener	IControllerListener
        //   0	89	2	paramInt	int
        //   3	80	3	localParcel1	Parcel
        //   7	71	4	localParcel2	Parcel
        //   75	12	5	localObject	Object
        //   25	46	6	localIBinder	IBinder
        // Exception table:
        //   from	to	target	type
        //   9	15	75	finally
        //   19	27	75	finally
        //   27	59	75	finally
      }
      
      /* Error */
      public void registerMonitor(IControllerMonitor paramIControllerMonitor, int paramInt)
        throws RemoteException
      {
        // Byte code:
        //   0: invokestatic 24	android/os/Parcel:obtain	()Landroid/os/Parcel;
        //   3: astore_3
        //   4: invokestatic 24	android/os/Parcel:obtain	()Landroid/os/Parcel;
        //   7: astore 4
        //   9: aload_3
        //   10: ldc 26
        //   12: invokevirtual 30	android/os/Parcel:writeInterfaceToken	(Ljava/lang/String;)V
        //   15: aload_1
        //   16: ifnull +52 -> 68
        //   19: aload_1
        //   20: invokeinterface 84 1 0
        //   25: astore 6
        //   27: aload_3
        //   28: aload 6
        //   30: invokevirtual 78	android/os/Parcel:writeStrongBinder	(Landroid/os/IBinder;)V
        //   33: aload_3
        //   34: iload_2
        //   35: invokevirtual 51	android/os/Parcel:writeInt	(I)V
        //   38: aload_0
        //   39: getfield 15	com/bda/controller/IControllerService$Stub$Proxy:mRemote	Landroid/os/IBinder;
        //   42: iconst_3
        //   43: aload_3
        //   44: aload 4
        //   46: iconst_0
        //   47: invokeinterface 36 5 0
        //   52: pop
        //   53: aload 4
        //   55: invokevirtual 39	android/os/Parcel:readException	()V
        //   58: aload 4
        //   60: invokevirtual 42	android/os/Parcel:recycle	()V
        //   63: aload_3
        //   64: invokevirtual 42	android/os/Parcel:recycle	()V
        //   67: return
        //   68: aconst_null
        //   69: astore 6
        //   71: goto -44 -> 27
        //   74: astore 5
        //   76: aload 4
        //   78: invokevirtual 42	android/os/Parcel:recycle	()V
        //   81: aload_3
        //   82: invokevirtual 42	android/os/Parcel:recycle	()V
        //   85: aload 5
        //   87: athrow
        // Local variable table:
        //   start	length	slot	name	signature
        //   0	88	0	this	Proxy
        //   0	88	1	paramIControllerMonitor	IControllerMonitor
        //   0	88	2	paramInt	int
        //   3	79	3	localParcel1	Parcel
        //   7	70	4	localParcel2	Parcel
        //   74	12	5	localObject	Object
        //   25	45	6	localIBinder	IBinder
        // Exception table:
        //   from	to	target	type
        //   9	15	74	finally
        //   19	27	74	finally
        //   27	58	74	finally
      }
      
      public void sendMessage(int paramInt1, int paramInt2)
        throws RemoteException
      {
        Parcel localParcel1 = Parcel.obtain();
        Parcel localParcel2 = Parcel.obtain();
        try
        {
          localParcel1.writeInterfaceToken("com.bda.controller.IControllerService");
          localParcel1.writeInt(paramInt1);
          localParcel1.writeInt(paramInt2);
          this.mRemote.transact(9, localParcel1, localParcel2, 0);
          localParcel2.readException();
          return;
        }
        finally
        {
          localParcel2.recycle();
          localParcel1.recycle();
        }
      }
      
      /* Error */
      public void unregisterListener(IControllerListener paramIControllerListener, int paramInt)
        throws RemoteException
      {
        // Byte code:
        //   0: invokestatic 24	android/os/Parcel:obtain	()Landroid/os/Parcel;
        //   3: astore_3
        //   4: invokestatic 24	android/os/Parcel:obtain	()Landroid/os/Parcel;
        //   7: astore 4
        //   9: aload_3
        //   10: ldc 26
        //   12: invokevirtual 30	android/os/Parcel:writeInterfaceToken	(Ljava/lang/String;)V
        //   15: aload_1
        //   16: ifnull +52 -> 68
        //   19: aload_1
        //   20: invokeinterface 75 1 0
        //   25: astore 6
        //   27: aload_3
        //   28: aload 6
        //   30: invokevirtual 78	android/os/Parcel:writeStrongBinder	(Landroid/os/IBinder;)V
        //   33: aload_3
        //   34: iload_2
        //   35: invokevirtual 51	android/os/Parcel:writeInt	(I)V
        //   38: aload_0
        //   39: getfield 15	com/bda/controller/IControllerService$Stub$Proxy:mRemote	Landroid/os/IBinder;
        //   42: iconst_2
        //   43: aload_3
        //   44: aload 4
        //   46: iconst_0
        //   47: invokeinterface 36 5 0
        //   52: pop
        //   53: aload 4
        //   55: invokevirtual 39	android/os/Parcel:readException	()V
        //   58: aload 4
        //   60: invokevirtual 42	android/os/Parcel:recycle	()V
        //   63: aload_3
        //   64: invokevirtual 42	android/os/Parcel:recycle	()V
        //   67: return
        //   68: aconst_null
        //   69: astore 6
        //   71: goto -44 -> 27
        //   74: astore 5
        //   76: aload 4
        //   78: invokevirtual 42	android/os/Parcel:recycle	()V
        //   81: aload_3
        //   82: invokevirtual 42	android/os/Parcel:recycle	()V
        //   85: aload 5
        //   87: athrow
        // Local variable table:
        //   start	length	slot	name	signature
        //   0	88	0	this	Proxy
        //   0	88	1	paramIControllerListener	IControllerListener
        //   0	88	2	paramInt	int
        //   3	79	3	localParcel1	Parcel
        //   7	70	4	localParcel2	Parcel
        //   74	12	5	localObject	Object
        //   25	45	6	localIBinder	IBinder
        // Exception table:
        //   from	to	target	type
        //   9	15	74	finally
        //   19	27	74	finally
        //   27	58	74	finally
      }
      
      /* Error */
      public void unregisterMonitor(IControllerMonitor paramIControllerMonitor, int paramInt)
        throws RemoteException
      {
        // Byte code:
        //   0: invokestatic 24	android/os/Parcel:obtain	()Landroid/os/Parcel;
        //   3: astore_3
        //   4: invokestatic 24	android/os/Parcel:obtain	()Landroid/os/Parcel;
        //   7: astore 4
        //   9: aload_3
        //   10: ldc 26
        //   12: invokevirtual 30	android/os/Parcel:writeInterfaceToken	(Ljava/lang/String;)V
        //   15: aload_1
        //   16: ifnull +52 -> 68
        //   19: aload_1
        //   20: invokeinterface 84 1 0
        //   25: astore 6
        //   27: aload_3
        //   28: aload 6
        //   30: invokevirtual 78	android/os/Parcel:writeStrongBinder	(Landroid/os/IBinder;)V
        //   33: aload_3
        //   34: iload_2
        //   35: invokevirtual 51	android/os/Parcel:writeInt	(I)V
        //   38: aload_0
        //   39: getfield 15	com/bda/controller/IControllerService$Stub$Proxy:mRemote	Landroid/os/IBinder;
        //   42: iconst_4
        //   43: aload_3
        //   44: aload 4
        //   46: iconst_0
        //   47: invokeinterface 36 5 0
        //   52: pop
        //   53: aload 4
        //   55: invokevirtual 39	android/os/Parcel:readException	()V
        //   58: aload 4
        //   60: invokevirtual 42	android/os/Parcel:recycle	()V
        //   63: aload_3
        //   64: invokevirtual 42	android/os/Parcel:recycle	()V
        //   67: return
        //   68: aconst_null
        //   69: astore 6
        //   71: goto -44 -> 27
        //   74: astore 5
        //   76: aload 4
        //   78: invokevirtual 42	android/os/Parcel:recycle	()V
        //   81: aload_3
        //   82: invokevirtual 42	android/os/Parcel:recycle	()V
        //   85: aload 5
        //   87: athrow
        // Local variable table:
        //   start	length	slot	name	signature
        //   0	88	0	this	Proxy
        //   0	88	1	paramIControllerMonitor	IControllerMonitor
        //   0	88	2	paramInt	int
        //   3	79	3	localParcel1	Parcel
        //   7	70	4	localParcel2	Parcel
        //   74	12	5	localObject	Object
        //   25	45	6	localIBinder	IBinder
        // Exception table:
        //   from	to	target	type
        //   9	15	74	finally
        //   19	27	74	finally
        //   27	58	74	finally
      }
    }
  }
}


/* Location:           E:\Dropbox\Dropbox\RealRacingHack\Decompile\install_dex2jar.jar
 * Qualified Name:     com.bda.controller.IControllerService
 * JD-Core Version:    0.7.0.1
 */